MANIFEST.in
setup.py
src/django_locality.egg-info/PKG-INFO
src/django_locality.egg-info/SOURCES.txt
src/django_locality.egg-info/dependency_links.txt
src/django_locality.egg-info/not-zip-safe
src/django_locality.egg-info/requires.txt
src/django_locality.egg-info/top_level.txt
src/locality/__init__.py
src/locality/forms.py
src/locality/managers.py
src/locality/models.py
src/locality/settings.py
src/locality/tests.py
src/locality/urls.py
src/locality/views.py
src/locality/fixtures/locality.json
src/locality/migrations/0001_initial.py
src/locality/migrations/__init__.py