Metadata-Version: 1.0
Name: django-locality
Version: 0.2.2
Summary: Countries and territories, made usable.
Home-page: https://github.com/rfkrocktk/django-locality
Author: Naftuli Tzvi Kay
Author-email: rfkrocktk@gmail.com
License: AGPL
Platform: UNKNOWN
